mcp_wolfram_alpha/__init__.py
mcp_wolfram_alpha/server.py
mcp_wolfram_alpha/wolfram_client.py
iflow_mcp_mcp_wolfram_alpha-0.2.2.dist-info/METADATA
iflow_mcp_mcp_wolfram_alpha-0.2.2.dist-info/WHEEL
iflow_mcp_mcp_wolfram_alpha-0.2.2.dist-info/entry_points.txt
iflow_mcp_mcp_wolfram_alpha-0.2.2.dist-info/licenses/LICENSE
iflow_mcp_mcp_wolfram_alpha-0.2.2.dist-info/RECORD
