Metadata-Version: 2.4
Name: iflow-mcp_mcp-wolfram-alpha
Version: 0.2.2
Summary: A MCP server to connect to wolfram alpha API.
Author-email: TerminalMan <84923604+SecretiveShell@users.noreply.github.com>
License-File: LICENSE
Requires-Python: >=3.12
Requires-Dist: httpx>=0.28.1
Requires-Dist: mcp>=1.2.0
